LICENSE
README.rst
setup.cfg
setup.py
s3dir.egg-info/PKG-INFO
s3dir.egg-info/SOURCES.txt
s3dir.egg-info/dependency_links.txt
s3dir.egg-info/entry_points.txt
s3dir.egg-info/not-zip-safe
s3dir.egg-info/requires.txt
s3dir.egg-info/top_level.txt
s3dir_src/__init__.py
s3dir_src/run.py
s3dir_src/lib/__init__.py
s3dir_src/lib/action.py
s3dir_src/lib/color.py
s3dir_src/lib/data.py
s3dir_src/lib/keyhandler.py
s3dir_src/lib/s3.py
s3dir_src/lib/textmode.py