Metadata-Version: 2.1
Name: s3dir
Version: 1.0.2
Summary: CLI File manager with S3 and Kubernetes
Home-page: https://github.com/rainygirl/s3dir
Author: Lee JunHaeng
Author-email: rainygirl@gmail.com
License: MIT License
Keywords: S3,Kubernetes,CLI,command line,terminal
Platform: UNKNOWN
Classifier: Environment :: Console
Classifier: License :: OSI Approved :: MIT License
Classifier: Operating System :: OS Independent
Classifier: Programming Language :: Python :: 3.9
Requires-Python: >=3.9
License-File: LICENSE
